{"title": "Woman Making a Face in Car", "description": "A woman wearing glasses and a blue sweater is seated in the driver's seat of a silver vintage car, sticking her tongue out playfully. The vehicle's interior shows a dashboard with classic design elements. The background includes dry grass and part of a road.", "color": "color", "images": ["/Users/harrison/scans/003/2024-08-01-16-54_0001x1920.jpg"], "hash": "646236942f5dc567ead50a34221c29c8", "ts": 1752860317.010635, "tags": ["car", "woman", "playful", "vintage", "tongue"], "date": ""}